rtl/fsm.v
/*
 * Module fsm
 *
 * Inputs: sclk_edge, cs, rw
 * Outputs: miso_buff, dm_we, addr_we, sr_we
 * Function: miso_buff enables output to master, use dm_we to write to
 * memory, addr_we to select an address of data memory, and sr_we to
 * parallel load the shift register.
 *
 * The states which control these outputs are:
 * - 0: Begin the transaction by allowing the address of the data
 *     memory to be selected and proceed to state 1.
 * - 1: Load the first 7 bits of data into the address and then proceed
 *   to state 2.
 * - 2: Branch for the value of RW.
 * - 3: Read: Enable the miso_pin and close parallel load (sr) of the
 *   shift register and then proceed tho state 4.
 * - 4: Disable miso_pin and revert to state 0.
 * - 5: Write MOSI to the selected address and then revert to state 0.
 */

`define BEGIN 3'd0
`define LOAD_ADDRESS 3'd1
`define HANDLE_READ_WRITE 3'd2
`define START_READ 3'd3
`define END_READ 3'd4
`define WRITE 3'd5

module fsm
  (
   input      sclk_edge, // Positive edge of the serial clock
              cs,  // Chip Select
              rw,   // Bit determining whether a read or write operation is occurring
   output reg miso_buff,
   dm_we,   // Date Memory Write Enable
   addr_we,   // Address Write enable
   sr_we    // Shift Register Write Enable
   );

   // Keep track of the amount of bits of data loaded.
   reg [3:0]  counter = 0;

   // Keep track of the current state.
   reg [2:0]  state = `BEGIN;

   always @(posedge sclk_edge) begin
      // If cs is high, do nothing.
      if (cs) begin
         state <= `BEGIN;
         miso_buff <= 0;
         dm_we <= 0;
         addr_we <= 0;
         sr_we <= 0;
         counter <= 0;
      end
      else begin
         case (state)

           // Begin the transaction
           `BEGIN: begin
              addr_we <= 1;
              state <= `LOAD_ADDRESS;
           end

           // Load the first 7 bits of data for the address.
           `LOAD_ADDRESS: begin
              counter <= counter + 1;
              if (counter == 6) begin
                 state <= `HANDLE_READ_WRITE;
                 counter <= 0;
                 addr_we <= 0;
              end
           end

           // Handle RW
           `HANDLE_READ_WRITE: begin
              // Read when rw high, write when rw low
              if (rw) begin
                 sr_we <= 1;
                 state <= `START_READ;
              end
              else begin
                 dm_we <= 1;
                 state <= `WRITE;
              end
           end

           // Read operation:
           `START_READ: begin
              sr_we <= 0;
              miso_buff <= 1;
              state <= `END_READ;
           end

           // Stop writing to miso
           `END_READ: begin
              if (counter == 7) begin
                 state <= `BEGIN;
                 counter <= 0;
                 miso_buff <= 0;
              end
              else begin
                 counter <= counter + 1;
              end
           end

           // Write to datamemory for 8 bits.
           `WRITE: begin
              if (counter == 8) begin
                 dm_we <= 0;
                 state <= `BEGIN;
                 counter <= 0;
              end
              else begin
                 counter <= counter + 1;
              end
           end
         endcase
      end
   end

endmodule

rtl/fsm.t.v
`include "fsm.v"
module testfsm();
   reg shift_reg_out_p = 0;
   reg cs = 1;
   reg sclk = 0;

   wire miso_buff, dm_we, addr_we, sr_we;

   fsm f
     (
      .sclk_edge(sclk),
      .cs(cs),
      .rw(shift_reg_out_p),
      .miso_buff(miso_buff),
      .dm_we(dm_we),
      .addr_we(addr_we),
      .sr_we(sr_we)
      );

   always #1 sclk = !sclk;
   initial begin
      $dumpfile("fsm.vcd");
      $dumpvars();
      #2 cs = 0;
      shift_reg_out_p = 0;
      #18 shift_reg_out_p = 1;
      #16 $finish;
   end
endmodule

rtl/fsm.vcd
$date
	Mon Oct 15 23:52:09 2018
$end
$version
	Icarus Verilog
$end
$timescale
	1s
$end
$scope module testfsm $end
$var wire 1 ! sr_we $end
$var wire 1 " miso_buff $end
$var wire 1 # dm_we $end
$var wire 1 $ addr_we $end
$var reg 1 % cs $end
$var reg 1 & sclk $end
$var reg 1 ' shift_reg_out_p $end
$scope module f $end
$var wire 1 % cs $end
$var wire 1 ' rw $end
$var wire 1 & sclk_edge $end
$var reg 1 $ addr_we $end
$var reg 4 ( counter [3:0] $end
$var reg 1 # dm_we $end
$var reg 1 " miso_buff $end
$var reg 1 ! sr_we $end
$var reg 3 ) state [2:0] $end
$upscope $end
$upscope $end
$enddefinitions $end
#0
$dumpvars
b0 )
b0 (
0'
0&
1%
x$
x#
x"
x!
$end
#1
0!
0$
0#
0"
1&
#2
0&
0%
#3
b1 )
1$
1&
#4
0&
#5
b1 (
1&
#6
0&
#7
b10 (
1&
#8
0&
#9
b11 (
1&
#10
0&
#11
b100 (
1&
#12
0&
#13
b101 (
1&
#14
0&
#15
b110 (
1&
#16
0&
#17
0$
b10 )
b0 (
1&
#18
0&
#19
b101 )
1#
1&
#20
0&
1'
#21
b1 (
1&
#22
0&
#23
b10 (
1&
#24
0&
#25
b11 (
1&
#26
0&
#27
b100 (
1&
#28
0&
#29
b101 (
1&
#30
0&
#31
b110 (
1&
#32
0&
#33
b111 (
1&
#34
0&
#35
b0 (
b0 )
0#
1&
