rtl/inputconditioner.sv
module inputconditioner
  (
   input      clk,
   input      noisysignal,
   output reg conditioned, positiveedge, negativeedge
   );
   parameter counterwidth = 3;
   parameter waittime = 3;

   reg [counterwidth - 1:0] counter = 0;
   reg                      synchronizer0 = 0;
   reg                      synchronizer1 = 0;

   always @(posedge clk) begin
      if (conditioned == synchronizer1) counter <= 0;
      else begin
         if (counter == waittime) begin
            counter <= 0;
            conditioned <= synchronizer1;
            if (synchronizer1 == 1) positiveedge <= 1;
            else negativeedge <= 1;
         end
         else counter <= counter + 1;
      end
      if (positiveedge) positiveedge <= 0;
      if (negativeedge) negativeedge <= 0;
      synchronizer0 <= noisysignal;
      synchronizer1 <= synchronizer0;
   end
endmodule

rtl/inputconditioner.t.sv
`include "inputconditioner.sv"

module testconditioner();
   reg clk, pin;
   wire conditioned, rising, falling;

   inputconditioner dut(
                        .clk(clk),
                        .noisysignal(pin),
                        .conditioned(conditioned),
                        .positiveedge(rising),
                        .negativeedge(falling)
                        );
   
   always #10 clk = !clk;

   initial begin
      $dumpfile("inputconditioner.vcd");
      $dumpvars();
      clk = 0;
      pin <= 1;
      #10 pin <= 0;
      #10 pin <= 1;
      #50 pin <= 0;
      #100 pin <= 0;
      #900 $finish;
   end
endmodule

rtl/inputconditioner.vcd
$date
	Fri Oct  5 16:16:46 2018
$end
$version
	Icarus Verilog
$end
$timescale
	1s
$end
$scope module testconditioner $end
$var wire 1 ! rising $end
$var wire 1 " falling $end
$var wire 1 # conditioned $end
$var reg 1 $ clk $end
$var reg 1 % pin $end
$scope module dut $end
$var wire 1 $ clk $end
$var wire 1 % noisysignal $end
$var reg 1 # conditioned $end
$var reg 3 & counter [2:0] $end
$var reg 1 " negativeedge $end
$var reg 1 ! positiveedge $end
$var reg 1 ' synchronizer0 $end
$var reg 1 ( synchronizer1 $end
$upscope $end
$upscope $end
$enddefinitions $end
#0
$dumpvars
0(
0'
b0 &
1%
0$
x#
x"
x!
$end
#10
1'
b1 &
0%
1$
#20
1%
0$
#30
1(
b10 &
1$
#40
0$
#50
b11 &
1$
#60
0$
#70
1!
1#
b0 &
0%
1$
#80
0$
#90
0'
0!
1$
#100
0$
#110
0(
1$
#120
0$
#130
b1 &
1$
#140
0$
#150
b10 &
1$
#160
0$
#170
b11 &
1$
#180
0$
#190
1"
0#
b0 &
1$
#200
0$
#210
0"
1$
