rtl/inputconditioner.v
//------------------------------------------------------------------------
// Input Conditioner
//    1) Synchronizes input to clock domain
//    2) Debounces input
//    3) Creates pulses at edge transitions
//------------------------------------------------------------------------

module inputconditioner
  (
   input      clk, // Clock domain to synchronize input to
   input      noisysignal, // (Potentially) noisy input signal
   output reg conditioned, positiveedge, negativeedge
   // Conditioned output signal
   // 1 clk pulse at rising edge of conditioned
   // 1 clk pulse at falling edge of conditioned
   );
   parameter counterwidth = 3; // Counter size, in bits, >= log2(waittime)
   parameter waittime = 3; // Debounce delay, in clock cycles

   reg [counterwidth - 1:0] counter = 0;
   reg                      synchronizer0 = 0;
   reg                      synchronizer1 = 0;

   always @(posedge clk) begin
     if (conditioned !== 0 && conditioned !== 1) begin
         conditioned <= 0;
         positiveedge <= 0;
         negativeedge <= 0;
       end
      if (conditioned == synchronizer1) counter <= 0;
      else begin
         if (counter == waittime) begin
            counter <= 0;
            conditioned <= synchronizer1;
            if (synchronizer1 == 1) positiveedge <= 1;
            else negativeedge <= 1;
         end
         else counter <= counter + 1;
      end
      if (positiveedge) positiveedge <= 0;
      if (negativeedge) negativeedge <= 0;
      synchronizer0 <= noisysignal;
      synchronizer1 <= synchronizer0;
   end
endmodule

rtl/inputconditioner.t.v
`timescale 1 ns / 1 ps
`include "inputconditioner.v"

module testconditioner();
   reg clk, pin;
   wire conditioned, rising, falling;

   inputconditioner dut(
                        .clk(clk),
                        .noisysignal(pin),
                        .conditioned(conditioned),
                        .positiveedge(rising),
                        .negativeedge(falling)
                        );
   // Generate clock (50MHz)
   initial clk=0;
   always #10 clk = !clk; // 50MHz Clock

   // Should suppress glitches up to 79 ns
   initial begin
      $dumpfile("inputconditioner.vcd");
      $dumpvars();
      clk = 0;
      pin <= 0;
      #80 pin <= 0;
      #80 pin <= 1;
      #80 pin <= 0;
      #79 pin <= 1;
      #80 pin <= 0;
      #20 pin <= 1;
      #80 pin <= 1;
      #30 pin <= 1;
      #10 pin <= 0;
      #80 pin <= 1;
      #80 pin <= 0;
      #20 pin <= 1;
      #80 pin <= 0;
      #80 pin <= 1;
      #30 pin <= 0;
      #80 pin <= 1;
      #100 $finish;
   end
endmodule

rtl/inputconditioner.vcd
$date
	Sun Oct  7 19:31:36 2018
$end
$version
	Icarus Verilog
$end
$timescale
	1ps
$end
$scope module testconditioner $end
$var wire 1 ! conditioned $end
$var wire 1 " falling $end
$var wire 1 # rising $end
$var reg 1 $ clk $end
$var reg 1 % pin $end
$scope module dut $end
$var wire 1 & clk $end
$var wire 1 ' noisysignal $end
$var reg 1 ( conditioned $end
$var reg 3 ) counter [2:0] $end
$var reg 1 * negativeedge $end
$var reg 1 + positiveedge $end
$var reg 1 , synchronizer0 $end
$var reg 1 - synchronizer1 $end
$upscope $end
$upscope $end
$enddefinitions $end
#0
$dumpvars
0-
0,
x+
x*
b0 )
x(
0'
0&
0%
0$
x#
x"
x!
$end
#10000
b1 )
0*
0"
0+
0#
0(
0!
1$
1&
#20000
0$
0&
#30000
b0 )
1$
1&
#40000
0$
0&
#50000
1$
1&
#60000
0$
0&
#70000
1$
1&
#80000
0$
0&
#90000
1$
1&
#100000
0$
0&
#110000
1$
1&
#120000
0$
0&
#130000
1$
1&
#140000
0$
0&
#150000
1$
1&
#160000
1%
1'
0$
0&
#170000
1,
1$
1&
#180000
0$
0&
#190000
1-
1$
1&
#200000
0$
0&
#210000
b1 )
1$
1&
#220000
0$
0&
#230000
b10 )
1$
1&
#240000
0%
0'
0$
0&
#250000
0,
b11 )
1$
1&
#260000
0$
0&
#270000
0-
1+
1#
1(
1!
b0 )
1$
1&
#280000
0$
0&
#290000
0+
0#
b1 )
1$
1&
#300000
0$
0&
#310000
b10 )
1$
1&
#319000
1%
1'
#320000
0$
0&
#330000
1,
b11 )
1$
1&
#340000
0$
0&
#350000
1-
1*
1"
0(
0!
b0 )
1$
1&
#360000
0$
0&
#370000
0*
0"
b1 )
1$
1&
#380000
0$
0&
#390000
b10 )
1$
1&
#399000
0%
0'
#400000
0$
0&
#410000
0,
b11 )
1$
1&
#419000
1%
1'
#420000
0$
0&
#430000
0-
1,
1+
1#
1(
1!
b0 )
1$
1&
#440000
0$
0&
#450000
1-
0+
0#
b1 )
1$
1&
#460000
0$
0&
#470000
b0 )
1$
1&
#480000
0$
0&
#490000
1$
1&
#500000
0$
0&
#510000
1$
1&
#520000
0$
0&
#530000
1$
1&
#539000
0%
0'
#540000
0$
0&
#550000
0,
1$
1&
#560000
0$
0&
#570000
0-
1$
1&
#580000
0$
0&
#590000
b1 )
1$
1&
#600000
0$
0&
#610000
b10 )
1$
1&
#619000
1%
1'
#620000
0$
0&
#630000
1,
b11 )
1$
1&
#640000
0$
0&
#650000
1-
1*
1"
0(
0!
b0 )
1$
1&
#660000
0$
0&
#670000
0*
0"
b1 )
1$
1&
#680000
0$
0&
#690000
b10 )
1$
1&
#699000
0%
0'
#700000
0$
0&
#710000
0,
b11 )
1$
1&
#719000
1%
1'
#720000
0$
0&
#730000
0-
1,
1+
1#
1(
1!
b0 )
1$
1&
#740000
0$
0&
#750000
1-
0+
0#
b1 )
1$
1&
#760000
0$
0&
#770000
b0 )
1$
1&
#780000
0$
0&
#790000
1$
1&
#799000
0%
0'
#800000
0$
0&
#810000
0,
1$
1&
#820000
0$
0&
#830000
0-
1$
1&
#840000
0$
0&
#850000
b1 )
1$
1&
#860000
0$
0&
#870000
b10 )
1$
1&
#879000
1%
1'
#880000
0$
0&
#890000
1,
b11 )
1$
1&
#900000
0$
0&
#909000
0%
0'
#910000
1-
0,
1*
1"
0(
0!
b0 )
1$
1&
#920000
0$
0&
#930000
0-
0*
0"
b1 )
1$
1&
#940000
0$
0&
#950000
b0 )
1$
1&
#960000
0$
0&
#970000
1$
1&
#980000
0$
0&
#989000
1%
1'
#990000
1,
1$
1&
#1000000
0$
0&
#1010000
1-
1$
1&
#1020000
0$
0&
#1030000
b1 )
1$
1&
#1040000
0$
0&
#1050000
b10 )
1$
1&
#1060000
0$
0&
#1070000
b11 )
1$
1&
