rtl/fsm.v
/*
 * Module fsm
 *
 * Inputs: sclk_edge, cs, rw
 * Outputs: miso_buff, dm_we, addr_we, sr_we
 * Function: miso_buff enables output to master, use dm_we to write to
 * memory, addr_we to select an address of data memory, and sr_we to
 * parallel load the shift register.
 *
 * The states which control these outputs are:
 * - 0: Begin the transaction by allowing the address of the data
 *     memory to be selected and proceed to state 1.
 * - 1: Load the first 7 bits of data into the address and then proceed
 *   to state 2.
 * - 2: Branch for the value of RW.
 * - 3: Read: Enable the miso_pin and close parallel load (sr) of the
 *   shift register and then proceed tho state 4.
 * - 4: Disable miso_pin and revert to state 0.
 * - 5: Write MOSI to the selected address and then revert to state 0.
 */

`define BEGIN 3'd0
`define LOAD_ADDRESS 3'd1
`define HANDLE_READ_WRITE 3'd2
`define START_READ 3'd3
`define END_READ 3'd4
`define WRITE 3'd5

module fsm
  (
   input      sclk_edge, // Positive edge of the serial clock
              cs,  // Chip Select
              rw,   // Bit determining whether a read or write operation is occurring
   output reg miso_buff,
   dm_we,   // Date Memory Write Enable
   addr_we,   // Address Write enable
   sr_we    // Shift Register Write Enable
   );

   // Keep track of the amount of bits of data loaded.
   reg [3:0]  counter = 0;

   // Keep track of the current state.
   reg [2:0]  state = `BEGIN;

   always @(posedge sclk_edge) begin
      // If cs is high, do nothing.
      if (cs) begin
         state <= `BEGIN;
         miso_buff <= 0;
         dm_we <= 0;
         addr_we <= 0;
         sr_we <= 0;
         counter <= 0;
      end
      else begin
         case (state)

           // Begin the transaction
           `BEGIN: begin
              addr_we <= 1;
              state <= `LOAD_ADDRESS;
           end

           // Load the first 7 bits of data for the address.
           `LOAD_ADDRESS: begin
              counter <= counter + 1;
              if (counter == 6) begin
                 state <= `HANDLE_READ_WRITE;
                 counter <= 0;
                 addr_we <= 0;
              end
           end

           // Handle RW
           `HANDLE_READ_WRITE: begin
              // Read when rw high, write when rw low
              if (rw) begin
                 sr_we <= 1;
                 state <= `START_READ;
              end
              else begin
                 dm_we <= 1;
                 state <= `WRITE;
              end
           end

           // Read operation:
           `START_READ: begin
              sr_we <= 0;
              miso_buff <= 1;
              state <= `END_READ;
           end

           // Stop writing to miso
           `END_READ: begin
              if (counter == 7) begin
                 state <= `BEGIN;
                 counter <= 0;
                 miso_buff <= 0;
              end
              else begin
                 counter <= counter + 1;
              end
           end

           // Write to datamemory for 8 bits.
           `WRITE: begin
              if (counter == 8) begin
                 dm_we <= 0;
                 state <= `BEGIN;
                 counter <= 0;
              end
              else begin
                 counter <= counter + 1;
              end
           end
         endcase
      end
   end

endmodule

fsm.t.v
`include "fsm.v"
module testfsm();
   reg shift_reg_out_p = 0;
   reg cs = 1;
   reg sclk = 0;

   wire miso_buff, dm_we, addr_we, sr_we;

   fsm f
     (
      .sclk_edge(sclk),
      .cs(cs),
      .rw(shift_reg_out_p),
      .miso_buff(miso_buff),
      .dm_we(dm_we),
      .addr_we(addr_we),
      .sr_we(sr_we)
//      .stateOut(stateOut)
      );

   always #1 sclk = !sclk;
   initial begin
      $dumpfile("fsmtwo.vcd");
      $dumpvars();
      // Write 8'b11111111 to 7'b0000000.
      #2 cs = 0;
      shift_reg_out_p = 0;
      #16 shift_reg_out_p = 1;
      #16 cs = 1;

      // Read address 7'b0000000
      #16 cs = 0;
      shift_reg_out_p = 0;
      #14 shift_reg_out_p = 1;
      #32 $finish;
   end
endmodule

fsmtwo.vcd
$date
	Tue Oct 16 19:02:34 2018
$end
$version
	Icarus Verilog
$end
$timescale
	1s
$end
$scope module testfsm $end
$var wire 1 ! sr_we $end
$var wire 1 " miso_buff $end
$var wire 1 # dm_we $end
$var wire 1 $ addr_we $end
$var reg 1 % cs $end
$var reg 1 & sclk $end
$var reg 1 ' shift_reg_out_p $end
$scope module f $end
$var wire 1 % cs $end
$var wire 1 ' rw $end
$var wire 1 & sclk_edge $end
$var reg 1 $ addr_we $end
$var reg 4 ( counter [3:0] $end
$var reg 1 # dm_we $end
$var reg 1 " miso_buff $end
$var reg 1 ! sr_we $end
$var reg 3 ) state [2:0] $end
$upscope $end
$upscope $end
$enddefinitions $end
#0
$dumpvars
b0 )
b0 (
0'
0&
1%
x$
x#
x"
x!
$end
#1
0!
1$
0#
0"
b1 )
1&
#2
0&
0%
#3
b1 (
1&
#4
0&
#5
b10 (
1&
#6
0&
#7
b11 (
1&
#8
0&
#9
b100 (
1&
#10
0&
#11
b101 (
1&
#12
0&
#13
b110 (
1&
#14
0&
#15
0$
b0 (
b10 )
1&
#16
0&
#17
b101 )
1&
#18
0&
1'
#19
b1 (
1&
#20
0&
#21
b10 (
1&
#22
0&
#23
b11 (
1&
#24
0&
#25
b100 (
1&
#26
0&
#27
b101 (
1&
#28
0&
#29
b110 (
1&
#30
0&
#31
b111 (
1&
#32
0&
#33
b0 (
b1 )
1#
1&
#34
0&
1%
#35
1$
0#
1&
#36
0&
#37
1&
#38
0&
#39
1&
#40
0&
#41
1&
#42
0&
#43
1&
#44
0&
#45
1&
#46
0&
#47
1&
#48
0&
#49
1&
#50
0&
0'
0%
#51
b1 (
1&
#52
0&
#53
b10 (
1&
#54
0&
#55
b11 (
1&
#56
0&
#57
b100 (
1&
#58
0&
#59
b101 (
1&
#60
0&
#61
b110 (
1&
#62
0&
#63
0$
b0 (
b10 )
1&
#64
0&
1'
#65
b11 )
1!
1&
#66
0&
#67
b100 )
1"
0!
1&
#68
0&
#69
b1 (
1&
#70
0&
#71
b10 (
1&
#72
0&
#73
b11 (
1&
#74
0&
#75
b100 (
1&
#76
0&
#77
b101 (
1&
#78
0&
#79
b110 (
1&
#80
0&
#81
b111 (
1&
#82
0&
#83
0"
b0 (
b1 )
1&
#84
0&
#85
b1 (
1$
1&
#86
0&
#87
b10 (
1&
#88
0&
#89
b11 (
1&
#90
0&
#91
b100 (
1&
#92
0&
#93
b101 (
1&
#94
0&
#95
b110 (
1&
