shiftregister.v
//------------------------------------------------------------------------
// Shift Register
//   Parameterized width (in bits)
//   Shift register can operate in two modes:
//      - serial in, parallel out
//      - parallel in, serial out
//------------------------------------------------------------------------

module shiftregister
  #(parameter width=8)
   (
    input               clk, peripheralClkEdge, parallelLoad,
    input [width - 1:0] parallelDataIn,
    input               serialDataIn,
    output [width-1:0]  parallelDataOut,
    output              serialDataOut
    );

   reg [width-1:0]      mem;

   assign parallelDataOut = mem;
   assign serialDataOut = mem[width - 1];

   always @(posedge clk) begin
      if (parallelLoad) mem <= parallelDataIn;
      else if (peripheralClkEdge) mem <= {mem[width-2:0], serialDataIn};
   end
endmodule

rtl/shiftregister.t.v
`include "shiftregister.v"

module testshiftregister
  #(parameter width = 8)
   ();

   reg clk, peripheralClkEdge, parallelLoad, serialDataIn;
   reg [width-1:0] parallelDataIn;
   wire [width-1:0] parallelDataOut;
   wire             serialDataOut;
   reg [7:0]        i, correct;
   
   shiftregister dut
     (
      .clk(clk),
      .peripheralClkEdge(peripheralClkEdge),
      .parallelLoad(parallelLoad),
      .parallelDataIn(parallelDataIn),
      .serialDataIn(serialDataIn),
      .parallelDataOut(parallelDataOut),
      .serialDataOut(serialDataOut)
      );

   initial clk=0;
   always #10 clk = !clk;

   initial begin
      $dumpfile("shiftregister.vcd");
      $dumpvars();
      peripheralClkEdge = 0;
      #20 parallelDataIn = 8'b0;
      serialDataIn = 1'b0;
      parallelLoad = 1;
      #20 peripheralClkEdge = 1;
      #20 peripheralClkEdge = 0;

      // Load serial with 1 and make sure that the ones are being shifted in
      for (i = 0; i < 8; i = i + 1)
        begin
           serialDataIn = 1;
           parallelDataIn = 0;
           parallelLoad = 0;
           #20 peripheralClkEdge = 1;
           #20 peripheralClkEdge = 0;
           correct = (1 << (i + 1)) - 1;
           if (parallelDataOut != correct) $display("failed on shifting in 1s, parallelDataOut is %d, should be %d", parallelDataOut, correct);
        end

      // Load serial with 0 and make sure that the 0s are being shifted in.
      for (i = 0; i < 8; i = i + 1)
        begin
           serialDataIn = 0;
           parallelDataIn = 0;
           parallelLoad = 0;
           #20 peripheralClkEdge = 1;
           #20 peripheralClkEdge = 0;
           correct = 256 - (1 << (i + 1));
           if (parallelDataOut != correct) $display("failed on shifting in 0s, parallelDataOut is %d, should be %d", parallelDataOut, correct);
        end
      #20 $finish;
   end

endmodule

shiftregister.vcd
$date
	Wed Oct 10 16:55:33 2018
$end
$version
	Icarus Verilog
$end
$timescale
	1s
$end
$scope module testshiftregister $end
$var wire 1 ! serialDataOut $end
$var wire 8 " parallelDataOut [7:0] $end
$var reg 1 # clk $end
$var reg 8 $ correct [7:0] $end
$var reg 8 % i [7:0] $end
$var reg 8 & parallelDataIn [7:0] $end
$var reg 1 ' parallelLoad $end
$var reg 1 ( peripheralClkEdge $end
$var reg 1 ) serialDataIn $end
$scope module dut $end
$var wire 1 # clk $end
$var wire 8 * parallelDataIn [7:0] $end
$var wire 8 + parallelDataOut [7:0] $end
$var wire 1 ' parallelLoad $end
$var wire 1 ( peripheralClkEdge $end
$var wire 1 ) serialDataIn $end
$var wire 1 ! serialDataOut $end
$var reg 8 , mem [7:0] $end
$upscope $end
$upscope $end
$enddefinitions $end
#0
$dumpvars
bx ,
bx +
bx *
x)
0(
x'
bx &
bx %
bx $
0#
bx "
x!
$end
#10
1#
#20
0#
1'
0)
b0 &
b0 *
#30
0!
b0 "
b0 +
b0 ,
1#
#40
0#
1(
#50
1#
#60
0#
0'
1)
b0 %
0(
#70
1#
#80
0#
1(
#90
b1 "
b1 +
b1 ,
1#
#100
0#
b1 %
b1 $
0(
#110
1#
#120
0#
1(
#130
b11 "
b11 +
b11 ,
1#
#140
0#
b10 %
b11 $
0(
#150
1#
#160
0#
1(
#170
b111 "
b111 +
b111 ,
1#
#180
0#
b11 %
b111 $
0(
#190
1#
#200
0#
1(
#210
b1111 "
b1111 +
b1111 ,
1#
#220
0#
b100 %
b1111 $
0(
#230
1#
#240
0#
1(
#250
b11111 "
b11111 +
b11111 ,
1#
#260
0#
b101 %
b11111 $
0(
#270
1#
#280
0#
1(
#290
b111111 "
b111111 +
b111111 ,
1#
#300
0#
b110 %
b111111 $
0(
#310
1#
#320
0#
1(
#330
b1111111 "
b1111111 +
b1111111 ,
1#
#340
0#
b111 %
b1111111 $
0(
#350
1#
#360
0#
1(
#370
1!
b11111111 "
b11111111 +
b11111111 ,
1#
#380
0#
0)
b0 %
b11111111 $
0(
#390
1#
#400
0#
1(
#410
b11111110 "
b11111110 +
b11111110 ,
1#
#420
0#
b1 %
b11111110 $
0(
#430
1#
#440
0#
1(
#450
b11111100 "
b11111100 +
b11111100 ,
1#
#460
0#
b10 %
b11111100 $
0(
#470
1#
#480
0#
1(
#490
b11111000 "
b11111000 +
b11111000 ,
1#
#500
0#
b11 %
b11111000 $
0(
#510
1#
#520
0#
1(
#530
b11110000 "
b11110000 +
b11110000 ,
1#
#540
0#
b100 %
b11110000 $
0(
#550
1#
#560
0#
1(
#570
b11100000 "
b11100000 +
b11100000 ,
1#
#580
0#
b101 %
b11100000 $
0(
#590
1#
#600
0#
1(
#610
b11000000 "
b11000000 +
b11000000 ,
1#
#620
0#
b110 %
b11000000 $
0(
#630
1#
#640
0#
1(
#650
b10000000 "
b10000000 +
b10000000 ,
1#
#660
0#
b111 %
b10000000 $
0(
#670
1#
#680
0#
1(
#690
0!
b0 "
b0 +
b0 ,
1#
#700
0#
b1000 %
b0 $
0(
